car_model_fixtures/__init__.py
car_model_fixtures/fixtures.py
car_model_fixtures/generate.py
car_model_fixtures-0.1.1.dist-info/LICENSE
car_model_fixtures-0.1.1.dist-info/METADATA
car_model_fixtures-0.1.1.dist-info/WHEEL
car_model_fixtures-0.1.1.dist-info/top_level.txt
car_model_fixtures-0.1.1.dist-info/RECORD
