Metadata-Version: 2.1
Name: car-model-fixtures
Version: 0.1.1
Summary: Aims to add popular continental car models by continent and year for realistic test data in the mobility sector
Home-page: https://github.com/Imperatus/car_model_fixtures
Author: Jurgen Buisman
Author-email: jurgen@twodamdigital.nl
License: MIT
Classifier: Development Status :: 1 - Planning
Classifier: License :: OSI Approved :: MIT License
Classifier: Operating System :: POSIX :: Linux
Classifier: Programming Language :: Python :: 3
License-File: LICENSE
